CSE 4010 Projects/Lab3a/fullAdder.v
//initialize wires
module halfAdder(op1, op2, sum, carry);

    //input wires
    input op1, op2;
    //output wires
    output sum, carry;

    //wire sum will be the same as the exclusive or of wires op1 and op2 
    assign sum = op1 ^ op2; // "^" = XOR operator
    //wire sum will be the same as the anding of wires op1 and op2 
    assign carry = op1 & op2; // "&" = AND operator    

endmodule

module fullAdder(A, B, carryIn, sum, carryOut);

    //input and output wires
    input A, B, carryIn;
    output sum, carryOut;

    //intermediary wires
    wire c, d, e;

    //half adder wire definitions for full adder 
    halfAdder u1(A, B, c, d);
    halfAdder u2(carryIn, c, e, f);

    //wire carryOut will be the same as the or of wires op1 and op2
    assign carryOut = f | d;
    //wire sum will be the same as wire e
    assign sum = e;

endmodule

CSE 4010 Projects/Lab3a/fullAdder_tb.v
//creates time limit and include fullAdder.v file
`timescale 1 ns / 1 ns
`include "fullAdder.v"

//creates test bench
module fullAdder_tb;

//denoted wires
reg A, B, carryIn;
wire sum, caryOut;

//creates instance of fullAdder
fullAdder uut(A, B, carryIn, sum, carryOut);

initial begin

    //creates a separate .vvp file and .vcd file for outputs
    $dumpfile("fullAdder_tb.vcd");
    $dumpvars(0, fullAdder_tb);

    //fullAdder gate
    {A, B, carryIn} = 3'd0; #20; 
    {A, B, carryIn} = 3'd1; #20; 
    {A, B, carryIn} = 3'd2; #20; 
    {A, B, carryIn} = 3'd3; #20; 
    {A, B, carryIn} = 3'd4; #20; 
    {A, B, carryIn} = 3'd5; #20; 
    {A, B, carryIn} = 3'd6; #20; 
    {A, B, carryIn} = 3'd7; #20; 
    //displays message to terminal
    $display("Finished additions!");

end

endmodule

CSE 4010 Projects/Lab3a/fullAdder_tb.vcd
$date
	Tue Apr 18 21:54:49 2023
$end
$version
	Icarus Verilog
$end
$timescale
	1ns
$end
$scope module fullAdder_tb $end
$var wire 1 ! sum $end
$var wire 1 " carryOut $end
$var reg 1 # A $end
$var reg 1 $ B $end
$var reg 1 % carryIn $end
$scope module uut $end
$var wire 1 # A $end
$var wire 1 $ B $end
$var wire 1 % carryIn $end
$var wire 1 " carryOut $end
$var wire 1 ! sum $end
$var wire 1 & f $end
$var wire 1 ' e $end
$var wire 1 ( d $end
$var wire 1 ) c $end
$scope module u1 $end
$var wire 1 ( carry $end
$var wire 1 # op1 $end
$var wire 1 $ op2 $end
$var wire 1 ) sum $end
$upscope $end
$scope module u2 $end
$var wire 1 & carry $end
$var wire 1 % op1 $end
$var wire 1 ) op2 $end
$var wire 1 ' sum $end
$upscope $end
$upscope $end
$upscope $end
$enddefinitions $end
#0
$dumpvars
0)
0(
0'
0&
0%
0$
0#
0"
0!
$end
#20
1!
1'
1%
#40
1)
1!
1'
1$
0%
#60
1"
0!
0'
1&
1%
#80
0"
1!
1'
0&
1#
0$
0%
#100
1"
0!
0'
1&
1%
#120
0)
1(
0!
0'
0&
1$
0%
#140
1!
1'
1%
