CSE 4010 Projects/lab3b/fullSubtractor.v
//initialize wires
module halfSubtractor(op1, op2, diff, borrow);


    //input wires
    input op1, op2;
    //output wires
    output diff, borrow;


    //wire diff will be the same as the exclusive or of wires op1 and op2
    assign diff = op1 ^ op2; // "^" = XOR operator
    //wire borrow will be the same as the and of wires not op1 and op2
    assign borrow = !op1 & op2; // "&" = AND operator, "!" = NOT operator    


endmodule

module fullSubtractor(A, B, Bin, diff, Bout);


    //input and output wires
    input A, B, Bin;
    output diff, Bout;


    //intermediary wires
    wire c, d, e;


    //half subtractor wire definitions for full subtractor
    halfSubtractor u1(A, B, c, d);
    halfSubtractor u2(Bin, c, e, f);


    //wire Bout will be the same as the or of wires f and d
    assign Bout = f | d;
    //wire diff will be the same as wire e
    assign diff = e;

endmodule

CSE 4010 Projects/lab3b/fullSubtractor_tb.v
//creates time limit and include fullSubtractor.v file
`timescale 1 ns / 1 ns
`include "fullSubtractor.v"

//creates test bench
module fullSubtractor_tb;

//denoted wires
reg A, B, Bin;
wire diff, Bout;

//creates instance of fullSubtractor
fullSubtractor uut(A, B, Bin, diff, Bout);

initial begin

    //creates a separate .vvp file and .vcd file for outputs
    $dumpfile("fullSubtractor_tb.vcd");
    $dumpvars(0, fullSubtractor_tb);


    //fullSubtractor gate
    {A, B, Bin} = 3'd0; #20;
    {A, B, Bin} = 3'd1; #20;
    {A, B, Bin} = 3'd2; #20;
    {A, B, Bin} = 3'd3; #20;
    {A, B, Bin} = 3'd4; #20;
    {A, B, Bin} = 3'd5; #20;
    {A, B, Bin} = 3'd6; #20;
    {A, B, Bin} = 3'd7; #20;
    //displays message to terminal
    $display("Finished subtractions!");
end
endmodule

CSE 4010 Projects/lab3b/fullSubtractor_tb.vcd
$date
	Tue Apr 18 23:23:16 2023
$end
$version
	Icarus Verilog
$end
$timescale
	1ns
$end
$scope module fullSubtractor_tb $end
$var wire 1 ! diff $end
$var wire 1 " Bout $end
$var reg 1 # A $end
$var reg 1 $ B $end
$var reg 1 % Bin $end
$scope module uut $end
$var wire 1 # A $end
$var wire 1 $ B $end
$var wire 1 % Bin $end
$var wire 1 " Bout $end
$var wire 1 ! diff $end
$var wire 1 & f $end
$var wire 1 ' e $end
$var wire 1 ( d $end
$var wire 1 ) c $end
$scope module u1 $end
$var wire 1 ( borrow $end
$var wire 1 ) diff $end
$var wire 1 # op1 $end
$var wire 1 $ op2 $end
$upscope $end
$scope module u2 $end
$var wire 1 & borrow $end
$var wire 1 ' diff $end
$var wire 1 % op1 $end
$var wire 1 ) op2 $end
$upscope $end
$upscope $end
$upscope $end
$enddefinitions $end
#0
$dumpvars
0)
0(
0'
0&
0%
0$
0#
0"
0!
$end
#20
1!
1'
1%
#40
1&
1"
1)
1(
1!
1'
1$
0%
#60
0!
0'
0&
1%
#80
0(
1!
1'
1&
1#
0$
0%
#100
0"
0!
0'
0&
1%
#120
0"
0)
0!
0'
0&
1$
0%
#140
1!
1'
1%
