CSE 4010 Projects/Lab4b/mux8x1.v
 //initialize wires
 module mux_8x1(a, b, c, d, e, f, g, h, sel0, sel1, sel2, out);

    // input wires
    input a, b, c, d, e, f, g, h, sel0, sel1, sel2;
    // output wire
    output out;

    /* wire out will be equal to the turnary operand of sel2 to two nested turnary operand of sel1 
    with two other nested turnary operand of sel0 and corresponding letters*/
    assign out = sel2 ? (sel1 ? (sel0 ? h : g) : (sel0 ? f : e)) : (sel1 ? (sel0 ? d : c) : (sel0 ? b : a));

 endmodule

CSE 4010 Projects/Lab4b/mux8x1_tb.v
//creates time limit and include mux8x1.v file
`timescale 1 ns / 1 ns
`include "mux8x1.v"

//creates test bench
module mux8x1_tb;

//denoted wires
reg A, B, C, D, E, F, G, H, Sel0, Sel1, Sel2;
wire O;

//creates instance of mux8x1
mux_8x1 uut(A, B, C, D, E, F, G, H, Sel0, Sel1, Sel2, O);

initial begin

    //creates a separate .vvp file and .vcd file for outputs
    $dumpfile("mux8x1_tb");
    $dumpvars(0, mux8x1_tb);

    //mux 8x1
    A = 0; B = 1; C = 0; D = 1; E = 0; F = 1; G = 0; H = 1;
    {Sel2, Sel1, Sel0} = 3'd0; #20;
    {Sel2, Sel1, Sel0} = 3'd1; #20;
    {Sel2, Sel1, Sel0} = 3'd2; #20;
    {Sel2, Sel1, Sel0} = 3'd3; #20;
    {Sel2, Sel1, Sel0} = 3'd4; #20;
    {Sel2, Sel1, Sel0} = 3'd5; #20;
    {Sel2, Sel1, Sel0} = 3'd6; #20;
    {Sel2, Sel1, Sel0} = 3'd7; #20;
    
    //displays message to terminal
    $display("Complete!");

end

endmodule

CSE 4010 Projects/Lab4b/mux8x1_tb.vcd
$date
	Thu May 11 19:06:08 2023
$end
$version
	Icarus Verilog
$end
$timescale
	1ns
$end
$scope module mux8x1_tb $end
$var wire 1 ! O $end
$var reg 1 " A $end
$var reg 1 # B $end
$var reg 1 $ C $end
$var reg 1 % D $end
$var reg 1 & E $end
$var reg 1 ' F $end
$var reg 1 ( G $end
$var reg 1 ) H $end
$var reg 1 * Sel0 $end
$var reg 1 + Sel1 $end
$var reg 1 , Sel2 $end
$scope module uut $end
$var wire 1 " a $end
$var wire 1 # b $end
$var wire 1 $ c $end
$var wire 1 % d $end
$var wire 1 & e $end
$var wire 1 ' f $end
$var wire 1 ( g $end
$var wire 1 ) h $end
$var wire 1 * sel0 $end
$var wire 1 + sel1 $end
$var wire 1 , sel2 $end
$var wire 1 ! out $end
$upscope $end
$upscope $end
$enddefinitions $end
#0
$dumpvars
0,
0+
0*
1)
0(
1'
0&
1%
0$
1#
0"
0!
$end
#20
1!
1*
#40
0!
1+
0*
#60
1!
1*
#80
0!
1,
0+
0*
#100
1!
1*
#120
0!
1+
0*
#140
1!
1*
